MCFXQ/__init__.py
MCFXQ/music.py
MCFXQ-0.1.0.dist-info/LICENSE
MCFXQ-0.1.0.dist-info/METADATA
MCFXQ-0.1.0.dist-info/WHEEL
MCFXQ-0.1.0.dist-info/top_level.txt
MCFXQ-0.1.0.dist-info/RECORD
