Metadata-Version: 2.1
Name: MCFXQ
Version: 0.1.0
Summary: 低音5到中音5到高音4#的乐器乐谱
Home-page: UNKNOWN
Author: 风汐琴
Author-email: 2062479194@qq.com
License: LICENSE
Platform: UNKNOWN
Classifier: Programming Language :: Python :: 3
Classifier: License :: OSI Approved :: MIT License
Classifier: Operating System :: OS Independent
Requires-Python: >=3.6
License-File: LICENSE
Requires-Dist: keyboard
